[
  {
    "_id": "5ce62cf60f7a4b093febbbb1",
    "index": 0,
    "guid": "43909f78-d611-4e50-ad58-200caa92549c",
    "isActive": true,
    "balance": "$3,056.33",
    "picture": "http://placehold.it/32x32",
    "age": 37,
    "eyeColor": "blue",
    "name": "Ernestine Rivas",
    "gender": "female",
    "company": "APPLIDECK",
    "email": "ernestinerivas@applideck.com",
    "phone": "+1 (854) 563-2598",
    "address": "982 Clifford Place, Dellview, Texas, 7336",
    "about": "Cupidatat ipsum sint in culpa dolore aute. Sint sint nisi amet laboris excepteur ad sint voluptate occaecat eu exercitation laboris officia. Culpa aliquip dolore sit voluptate dolor veniam consequat tempor elit magna ad fugiat duis aliquip. Exercitation aliquip ipsum anim qui anim qui occaecat sit dolor adipisicing. Dolor aute irure mollit id consequat velit nisi ea nulla aute. Irure officia occaecat elit magna fugiat incididunt excepteur do mollit labore.\r\n",
    "registered": "2014-07-12T02:04:26 -03:00",
    "latitude": -77.614191,
    "longitude": 50.890289,
    "tags": [
      "culpa",
      "qui",
      "veniam",
      "excepteur",
      "labore",
      "laboris",
      "incididunt"
    ],
    "friends": [
      {
        "id": 0,
        "name": "Johnson Duncan"
      },
      {
        "id": 1,
        "name": "Chavez Obrien"
      },
      {
        "id": 2,
        "name": "Boone Rose"
      }
    ],
    "greeting": "Hello, Ernestine Rivas! You have 5 unread messages.",
    "favoriteFruit": "apple"
  },
  {
    "_id": "5ce62cf6c4813efb2776b4ac",
    "index": 1,
    "guid": "10a217b9-3f4e-4ec3-8158-ed6e955c38d7",
    "isActive": true,
    "balance": "$1,436.50",
    "picture": "http://placehold.it/32x32",
    "age": 24,
    "eyeColor": "brown",
    "name": "Ayers Huffman",
    "gender": "male",
    "company": "DATAGENE",
    "email": "ayershuffman@datagene.com",
    "phone": "+1 (861) 463-3870",
    "address": "972 Juliana Place, Westmoreland, North Carolina, 2113",
    "about": "Culpa aliquip culpa labore officia ut velit ut et elit laborum dolore consectetur. Incididunt dolore mollit cillum velit minim id magna ut deserunt quis do fugiat. Duis Lorem voluptate sint dolore id eu nisi adipisicing magna veniam ut. Commodo sunt laborum dolor minim laboris adipisicing dolore.\r\n",
    "registered": "2017-07-09T11:04:10 -03:00",
    "latitude": -79.357062,
    "longitude": -46.588943,
    "tags": [
      "labore",
      "dolore",
      "et",
      "ullamco",
      "esse",
      "veniam",
      "do"
    ],
    "friends": [
      {
        "id": 0,
        "name": "Marylou Pruitt"
      },
      {
        "id": 1,
        "name": "Ross Haney"
      },
      {
        "id": 2,
        "name": "Nelson Colon"
      }
    ],
    "greeting": "Hello, Ayers Huffman! You have 6 unread messages.",
    "favoriteFruit": "strawberry"
  },
  {
    "_id": "5ce62cf6f3ba9193d1d1ec19",
    "index": 2,
    "guid": "20408ecf-94d9-4799-b06a-00f3c4f405c4",
    "isActive": false,
    "balance": "$1,474.12",
    "picture": "http://placehold.it/32x32",
    "age": 33,
    "eyeColor": "brown",
    "name": "Maritza Francis",
    "gender": "female",
    "company": "REVERSUS",
    "email": "maritzafrancis@reversus.com",
    "phone": "+1 (825) 578-2340",
    "address": "781 Argyle Road, Edgewater, Federated States Of Micronesia, 2544",
    "about": "Dolore incididunt cillum cillum velit non enim proident in duis. Cupidatat cillum anim id sunt est. Lorem ex eu ullamco ut. Deserunt aute aliqua culpa anim consectetur anim nulla ut. Aliqua cupidatat dolor et aute deserunt est voluptate. Labore occaecat Lorem excepteur reprehenderit dolor aliquip in exercitation esse dolor labore sint. Nulla do quis sint minim enim ullamco amet ullamco amet enim.\r\n",
    "registered": "2017-08-27T06:34:02 -03:00",
    "latitude": -25.795842,
    "longitude": 148.441735,
    "tags": [
      "veniam",
      "sit",
      "do",
      "laboris",
      "elit",
      "enim",
      "veniam"
    ],
    "friends": [
      {
        "id": 0,
        "name": "Fry Sherman"
      },
      {
        "id": 1,
        "name": "Porter Davidson"
      },
      {
        "id": 2,
        "name": "Esperanza Bird"
      }
    ],
    "greeting": "Hello, Maritza Francis! You have 8 unread messages.",
    "favoriteFruit": "strawberry"
  },
  {
    "_id": "5ce62cf6c97d75d49daf577a",
    "index": 3,
    "guid": "11a1d7e2-6495-4e1d-b7cd-49d1bc0e2247",
    "isActive": false,
    "balance": "$2,840.27",
    "picture": "http://placehold.it/32x32",
    "age": 23,
    "eyeColor": "brown",
    "name": "Cole Barlow",
    "gender": "male",
    "company": "CENTREXIN",
    "email": "colebarlow@centrexin.com",
    "phone": "+1 (979) 431-2199",
    "address": "663 Tillary Street, Waukeenah, Oklahoma, 2842",
    "about": "Labore id fugiat eu culpa quis amet esse ex eu esse est. Nisi ullamco sit consectetur velit nulla deserunt ad duis ad commodo occaecat ipsum tempor mollit. Non nulla reprehenderit qui tempor pariatur ad elit cupidatat reprehenderit aute ex voluptate irure. Cillum ea Lorem ea duis velit sit esse minim ut culpa cupidatat amet. Sunt Lorem cillum excepteur minim nulla culpa aute proident voluptate aliquip culpa fugiat irure. Culpa nostrud tempor in enim fugiat cillum anim ea proident enim mollit ullamco deserunt adipisicing. Sunt officia ullamco esse enim esse qui laboris in commodo irure.\r\n",
    "registered": "2016-03-15T05:35:07 -02:00",
    "latitude": -83.072951,
    "longitude": -150.50757,
    "tags": [
      "non",
      "cupidatat",
      "ad",
      "ullamco",
      "veniam",
      "minim",
      "Lorem"
    ],
    "friends": [
      {
        "id": 0,
        "name": "Jasmine Gomez"
      },
      {
        "id": 1,
        "name": "Shanna Foreman"
      },
      {
        "id": 2,
        "name": "Opal Fletcher"
      }
    ],
    "greeting": "Hello, Cole Barlow! You have 7 unread messages.",
    "favoriteFruit": "strawberry"
  },
  {
    "_id": "5ce62cf6204109502e263cee",
    "index": 4,
    "guid": "1a3c851e-539b-4f6f-a3ba-66660d2e94e0",
    "isActive": false,
    "balance": "$1,264.90",
    "picture": "http://placehold.it/32x32",
    "age": 31,
    "eyeColor": "brown",
    "name": "Shana Mcgowan",
    "gender": "female",
    "company": "POOCHIES",
    "email": "shanamcgowan@poochies.com",
    "phone": "+1 (945) 568-3631",
    "address": "900 Bainbridge Street, Shasta, New Mexico, 7496",
    "about": "Incididunt esse cupidatat pariatur quis consectetur adipisicing dolore excepteur tempor officia non. Veniam non occaecat reprehenderit amet consectetur tempor exercitation elit pariatur minim consequat. Reprehenderit esse amet ex eiusmod sint deserunt fugiat incididunt ullamco quis consectetur sint aute voluptate. Cillum ad proident incididunt cupidatat mollit est officia pariatur pariatur. Magna fugiat ex minim reprehenderit sint. Labore sit officia commodo do esse.\r\n",
    "registered": "2014-02-13T10:13:15 -02:00",
    "latitude": -7.727076,
    "longitude": 25.94923,
    "tags": [
      "ipsum",
      "minim",
      "ut",
      "dolor",
      "labore",
      "dolore",
      "non"
    ],
    "friends": [
      {
        "id": 0,
        "name": "Letitia Spears"
      },
      {
        "id": 1,
        "name": "Mcdonald Giles"
      },
      {
        "id": 2,
        "name": "Baldwin Downs"
      }
    ],
    "greeting": "Hello, Shana Mcgowan! You have 8 unread messages.",
    "favoriteFruit": "apple"
  }
]